{
  "data": [
    {
      "id": 1493729,
      "line3": "",
      "line2": "31-Jul-2020",
      "line1": "1721235315262394 - HSBC",
      "actions": [
        {
          "index": 1,
          "onClick": "id",
          "displayName": "INITIATE",
          "type": "BUTTON",
          "class": "p-button-text p-button-sm"
        }
      ]
    },
    {
      "id": 1493728,
      "line3": "",
      "line2": "31-Jul-2020",
      "line1": "1721235315262394 - CITYBANK",
      "actions": [
        {
          "index": 1,
          "onClick": "id",
          "displayName": "INITIATE",
          "type": "BUTTON",
          "class": "p-button-text p-button-sm"
        }
      ]
    },
    {
      "id": 1493727,
      "line3": "",
      "line2": "31-Jul-2020",
      "line1": "1721235315262324 - HSBC",
      "actions": [
        {
          "index": 1,
          "onClick": "id",
          "displayName": "INITIATE",
          "type": "BUTTON",
          "class": "p-button-text p-button-sm"
        }
      ]
    },
    {
      "id": 1493726,
      "line3": "",
      "line2": "31-Jul-2020",
      "line1": "1721235315262394 - HDFC",
      "actions": [
        {
          "index": 1,
          "onClick": "id",
          "displayName": "INITIATE",
          "type": "BUTTON",
          "class": "p-button-text p-button-sm"
        }
      ]
    },
    {
      "id": 1493751,
      "line3": "",
      "line2": "31-Jul-2020",
      "line1": "1721235315262394 - AU",
      "actions": [
        {
          "index": 1,
          "onClick": "id",
          "displayName": "INITIATE",
          "type": "BUTTON",
          "class": "p-button-text p-button-sm"
        }
      ]
    }
  ],
  "totalRecords": 5
}
