[
  { "headerName": "Batch No", "field": "id" },
  { "headerName": "Corporate Code", "field": "corporateCode" },
  { "headerName": "Corporate Client Code", "field": "corporateClientCode" },
  { "headerName": "Corporate Client Name", "field": "corporateClientName" },
  { "headerName": "Payment Mode", "field": "paymentMode" },
  { "headerName": "PaymentDate", "field": "paymentDate" },
  { "headerName": "Credit Account No", "field": "creditAccountNo" },
  { "headerName": "Payment Amount", "field": "paymentAmount" },
  { "headerName": "Status", "field": "status" }
]
